{"versionmap_countAny_full": {"SSLv3": 0, "TLSv1.0": 559, "TLSv1.1": 0, "TLSv1.2": 649931, "TLSv1.3draft18": 40029, "TLSv1.3draft19": 0, "TLSv1.3draft20": 0, "TLSv1.3draft21": 0, "TLSv1.3draft22": 0, "TLSv1.3draft23": 106516, "TLSv1.3draft24": 0, "TLSv1.3draft25": 0, "TLSv1.3draft26": 0, "TLSv1.3draft27": 0, "TLSv1.3draft28": 0, "TLSv1.3": 0}, "versionmap_countAny_sh": {"SSLv3": 2, "TLSv1.0": 10738, "TLSv1.1": 61, "TLSv1.2": 32358, "TLSv1.3draft18": 529, "TLSv1.3draft19": 0, "TLSv1.3draft20": 0, "TLSv1.3draft21": 0, "TLSv1.3draft22": 0, "TLSv1.3draft23": 69430, "TLSv1.3draft24": 0, "TLSv1.3draft25": 0, "TLSv1.3draft26": 0, "TLSv1.3draft27": 0, "TLSv1.3draft28": 0, "TLSv1.3": 0}, "versionmap_countAny_full_and_sh": {"SSLv3": 0, "TLSv1.0": 8, "TLSv1.1": 0, "TLSv1.2": 9692, "TLSv1.3draft18": 157, "TLSv1.3draft19": 0, "TLSv1.3draft20": 0, "TLSv1.3draft21": 0, "TLSv1.3draft22": 0, "TLSv1.3draft23": 58179, "TLSv1.3draft24": 0, "TLSv1.3draft25": 0, "TLSv1.3draft26": 0, "TLSv1.3draft27": 0, "TLSv1.3draft28": 0, "TLSv1.3": 0}, "versionmap_countAny_full_or_sh": {"SSLv3": 2, "TLSv1.0": 11289, "TLSv1.1": 61, "TLSv1.2": 672597, "TLSv1.3draft18": 40401, "TLSv1.3draft19": 0, "TLSv1.3draft20": 0, "TLSv1.3draft21": 0, "TLSv1.3draft22": 0, "TLSv1.3draft23": 117767, "TLSv1.3draft24": 0, "TLSv1.3draft25": 0, "TLSv1.3draft26": 0, "TLSv1.3draft27": 0, "TLSv1.3draft28": 0, "TLSv1.3": 0}, "full_latest": {"SSLv3": 0, "TLSv1.0": 442, "TLSv1.1": 0, "TLSv1.2": 648796, "TLSv1.3draft18": 38549, "TLSv1.3draft19": 0, "TLSv1.3draft20": 0, "TLSv1.3draft21": 0, "TLSv1.3draft22": 0, "TLSv1.3draft23": 105134, "TLSv1.3draft24": 0, "TLSv1.3draft25": 0, "TLSv1.3draft26": 0, "TLSv1.3draft27": 0, "TLSv1.3draft28": 0, "TLSv1.3": 0}, "full_preferred_over_sh_latest": {"SSLv3": 1, "TLSv1.0": 10615, "TLSv1.1": 61, "TLSv1.2": 671316, "TLSv1.3draft18": 38915, "TLSv1.3draft19": 0, "TLSv1.3draft20": 0, "TLSv1.3draft21": 0, "TLSv1.3draft22": 0, "TLSv1.3draft23": 113107, "TLSv1.3draft24": 0, "TLSv1.3draft25": 0, "TLSv1.3draft26": 0, "TLSv1.3draft27": 0, "TLSv1.3draft28": 0, "TLSv1.3": 0}, "full_or_sh_latest": {"SSLv3": 1, "TLSv1.0": 10635, "TLSv1.1": 61, "TLSv1.2": 670075, "TLSv1.3draft18": 38869, "TLSv1.3draft19": 0, "TLSv1.3draft20": 0, "TLSv1.3draft21": 0, "TLSv1.3draft22": 0, "TLSv1.3draft23": 114374, "TLSv1.3draft24": 0, "TLSv1.3draft25": 0, "TLSv1.3draft26": 0, "TLSv1.3draft27": 0, "TLSv1.3draft28": 0, "TLSv1.3": 0}, "full_and_sh_latest": {"SSLv3": 0, "TLSv1.0": 8, "TLSv1.1": 0, "TLSv1.2": 9671, "TLSv1.3draft18": 155, "TLSv1.3draft19": 0, "TLSv1.3draft20": 0, "TLSv1.3draft21": 0, "TLSv1.3draft22": 0, "TLSv1.3draft23": 57717, "TLSv1.3draft24": 0, "TLSv1.3draft25": 0, "TLSv1.3draft26": 0, "TLSv1.3draft27": 0, "TLSv1.3draft28": 0, "TLSv1.3": 0}, "multi_versions_full": 792921, "multi_versions_full_or_sh": 834014, "full": 792921, "full_or_SH": 834015, "full_and_SH": 71644, "443_refused": 24849, "all": 869775}