{"versionmap_countAny_full": {"SSLv3": 0, "TLSv1.0": 34240, "TLSv1.1": 1116, "TLSv1.2": 5355436, "TLSv1.3draft18": 69362, "TLSv1.3draft19": 0, "TLSv1.3draft20": 0, "TLSv1.3draft21": 1, "TLSv1.3draft22": 5, "TLSv1.3draft23": 625553, "TLSv1.3draft24": 0, "TLSv1.3draft25": 0, "TLSv1.3draft26": 0, "TLSv1.3draft27": 0, "TLSv1.3draft28": 0, "TLSv1.3": 0}, "versionmap_countAny_sh": {"SSLv3": 219, "TLSv1.0": 254804, "TLSv1.1": 1328, "TLSv1.2": 1800504, "TLSv1.3draft18": 1657, "TLSv1.3draft19": 4, "TLSv1.3draft20": 0, "TLSv1.3draft21": 4, "TLSv1.3draft22": 0, "TLSv1.3draft23": 69106, "TLSv1.3draft24": 0, "TLSv1.3draft25": 0, "TLSv1.3draft26": 0, "TLSv1.3draft27": 0, "TLSv1.3draft28": 0, "TLSv1.3": 0}, "versionmap_countAny_full_and_sh": {"SSLv3": 0, "TLSv1.0": 486, "TLSv1.1": 4, "TLSv1.2": 163410, "TLSv1.3draft18": 1008, "TLSv1.3draft19": 0, "TLSv1.3draft20": 0, "TLSv1.3draft21": 0, "TLSv1.3draft22": 0, "TLSv1.3draft23": 15722, "TLSv1.3draft24": 0, "TLSv1.3draft25": 0, "TLSv1.3draft26": 0, "TLSv1.3draft27": 0, "TLSv1.3draft28": 0, "TLSv1.3": 0}, "versionmap_countAny_full_or_sh": {"SSLv3": 219, "TLSv1.0": 288558, "TLSv1.1": 2440, "TLSv1.2": 6992530, "TLSv1.3draft18": 70011, "TLSv1.3draft19": 4, "TLSv1.3draft20": 0, "TLSv1.3draft21": 5, "TLSv1.3draft22": 5, "TLSv1.3draft23": 678937, "TLSv1.3draft24": 0, "TLSv1.3draft25": 0, "TLSv1.3draft26": 0, "TLSv1.3draft27": 0, "TLSv1.3draft28": 0, "TLSv1.3": 0}, "full_latest": {"SSLv3": 0, "TLSv1.0": 33714, "TLSv1.1": 1109, "TLSv1.2": 5350934, "TLSv1.3draft18": 63245, "TLSv1.3draft19": 0, "TLSv1.3draft20": 0, "TLSv1.3draft21": 1, "TLSv1.3draft22": 5, "TLSv1.3draft23": 622616, "TLSv1.3draft24": 0, "TLSv1.3draft25": 0, "TLSv1.3draft26": 0, "TLSv1.3draft27": 0, "TLSv1.3draft28": 0, "TLSv1.3": 0}, "full_preferred_over_sh_latest": {"SSLv3": 198, "TLSv1.0": 282350, "TLSv1.1": 2370, "TLSv1.2": 6986045, "TLSv1.3draft18": 63848, "TLSv1.3draft19": 4, "TLSv1.3draft20": 0, "TLSv1.3draft21": 5, "TLSv1.3draft22": 5, "TLSv1.3draft23": 671791, "TLSv1.3draft24": 0, "TLSv1.3draft25": 0, "TLSv1.3draft26": 0, "TLSv1.3draft27": 0, "TLSv1.3draft28": 0, "TLSv1.3": 0}, "full_or_sh_latest": {"SSLv3": 201, "TLSv1.0": 283190, "TLSv1.1": 2371, "TLSv1.2": 6984369, "TLSv1.3draft18": 63266, "TLSv1.3draft19": 4, "TLSv1.3draft20": 0, "TLSv1.3draft21": 5, "TLSv1.3draft22": 5, "TLSv1.3draft23": 673205, "TLSv1.3draft24": 0, "TLSv1.3draft25": 0, "TLSv1.3draft26": 0, "TLSv1.3draft27": 0, "TLSv1.3draft28": 0, "TLSv1.3": 0}, "full_and_sh_latest": {"SSLv3": 0, "TLSv1.0": 468, "TLSv1.1": 4, "TLSv1.2": 163117, "TLSv1.3draft18": 896, "TLSv1.3draft19": 0, "TLSv1.3draft20": 0, "TLSv1.3draft21": 0, "TLSv1.3draft22": 0, "TLSv1.3draft23": 15252, "TLSv1.3draft24": 0, "TLSv1.3draft25": 0, "TLSv1.3draft26": 0, "TLSv1.3draft27": 0, "TLSv1.3draft28": 0, "TLSv1.3": 0}, "multi_versions_full": 6071624, "multi_versions_full_or_sh": 8006419, "full": 6071624, "full_or_SH": 8006616, "full_and_SH": 190723, "443_refused": 4552343, "all": 13795256}