{"versionmap_countAny_full":{"SSLv3":0,"TLSv1.0":29,"TLSv1.1":0,"TLSv1.2":74990,"TLSv1.3draft18":0,"TLSv1.3draft19":0,"TLSv1.3draft20":0,"TLSv1.3draft21":0,"TLSv1.3draft22":0,"TLSv1.3draft23":0,"TLSv1.3draft24":0,"TLSv1.3draft25":0,"TLSv1.3draft26":0,"TLSv1.3draft27":0,"TLSv1.3draft28":4,"TLSv1.3":1234},"versionmap_countAny_sh":{"SSLv3":1,"TLSv1.0":762,"TLSv1.1":13,"TLSv1.2":17719,"TLSv1.3draft18":0,"TLSv1.3draft19":0,"TLSv1.3draft20":0,"TLSv1.3draft21":0,"TLSv1.3draft22":0,"TLSv1.3draft23":0,"TLSv1.3draft24":0,"TLSv1.3draft25":0,"TLSv1.3draft26":0,"TLSv1.3draft27":0,"TLSv1.3draft28":0,"TLSv1.3":24},"versionmap_countAny_full_and_sh":{"SSLv3":0,"TLSv1.0":0,"TLSv1.1":0,"TLSv1.2":2182,"TLSv1.3draft18":0,"TLSv1.3draft19":0,"TLSv1.3draft20":0,"TLSv1.3draft21":0,"TLSv1.3draft22":0,"TLSv1.3draft23":0,"TLSv1.3draft24":0,"TLSv1.3draft25":0,"TLSv1.3draft26":0,"TLSv1.3draft27":0,"TLSv1.3draft28":0,"TLSv1.3":18},"versionmap_countAny_full_or_sh":{"SSLv3":1,"TLSv1.0":791,"TLSv1.1":13,"TLSv1.2":90527,"TLSv1.3draft18":0,"TLSv1.3draft19":0,"TLSv1.3draft20":0,"TLSv1.3draft21":0,"TLSv1.3draft22":0,"TLSv1.3draft23":0,"TLSv1.3draft24":0,"TLSv1.3draft25":0,"TLSv1.3draft26":0,"TLSv1.3draft27":0,"TLSv1.3draft28":4,"TLSv1.3":1240},"full_latest":{"SSLv3":0,"TLSv1.0":24,"TLSv1.1":0,"TLSv1.2":74947,"TLSv1.3draft18":0,"TLSv1.3draft19":0,"TLSv1.3draft20":0,"TLSv1.3draft21":0,"TLSv1.3draft22":0,"TLSv1.3draft23":0,"TLSv1.3draft24":0,"TLSv1.3draft25":0,"TLSv1.3draft26":0,"TLSv1.3draft27":0,"TLSv1.3draft28":4,"TLSv1.3":743},"full_preferred_over_sh_latest":{"SSLv3":1,"TLSv1.0":745,"TLSv1.1":9,"TLSv1.2":90482,"TLSv1.3draft18":0,"TLSv1.3draft19":0,"TLSv1.3draft20":0,"TLSv1.3draft21":0,"TLSv1.3draft22":0,"TLSv1.3draft23":0,"TLSv1.3draft24":0,"TLSv1.3draft25":0,"TLSv1.3draft26":0,"TLSv1.3draft27":0,"TLSv1.3draft28":4,"TLSv1.3":746},"full_or_sh_latest":{"SSLv3":1,"TLSv1.0":750,"TLSv1.1":9,"TLSv1.2":90477,"TLSv1.3draft18":0,"TLSv1.3draft19":0,"TLSv1.3draft20":0,"TLSv1.3draft21":0,"TLSv1.3draft22":0,"TLSv1.3draft23":0,"TLSv1.3draft24":0,"TLSv1.3draft25":0,"TLSv1.3draft26":0,"TLSv1.3draft27":0,"TLSv1.3draft28":4,"TLSv1.3":746},"full_and_sh_latest":{"SSLv3":0,"TLSv1.0":0,"TLSv1.1":0,"TLSv1.2":2181,"TLSv1.3draft18":0,"TLSv1.3draft19":0,"TLSv1.3draft20":0,"TLSv1.3draft21":0,"TLSv1.3draft22":0,"TLSv1.3draft23":0,"TLSv1.3draft24":0,"TLSv1.3draft25":0,"TLSv1.3draft26":0,"TLSv1.3draft27":0,"TLSv1.3draft28":0,"TLSv1.3":16},"multi_versions_full":75718,"multi_versions_full_or_sh":91986,"full":75718,"full_or_SH":91987,"full_and_SH":2239,"443_refused":16558,"all":117267}
