{"versionmap_countAny_full": {"SSLv3": 0, "TLSv1.0": 4513, "TLSv1.1": 3, "TLSv1.2": 1644804, "TLSv1.3draft18": 2571, "TLSv1.3draft19": 0, "TLSv1.3draft20": 0, "TLSv1.3draft21": 0, "TLSv1.3draft22": 0, "TLSv1.3draft23": 53200, "TLSv1.3draft24": 0, "TLSv1.3draft25": 0, "TLSv1.3draft26": 0, "TLSv1.3draft27": 0, "TLSv1.3draft28": 60, "TLSv1.3": 57763}, "versionmap_countAny_sh": {"SSLv3": 9, "TLSv1.0": 625291, "TLSv1.1": 387, "TLSv1.2": 213384, "TLSv1.3draft18": 2338, "TLSv1.3draft19": 0, "TLSv1.3draft20": 0, "TLSv1.3draft21": 0, "TLSv1.3draft22": 0, "TLSv1.3draft23": 9162, "TLSv1.3draft24": 0, "TLSv1.3draft25": 0, "TLSv1.3draft26": 0, "TLSv1.3draft27": 0, "TLSv1.3draft28": 0, "TLSv1.3": 558}, "versionmap_countAny_full_and_sh": {"SSLv3": 0, "TLSv1.0": 97, "TLSv1.1": 0, "TLSv1.2": 37532, "TLSv1.3draft18": 2315, "TLSv1.3draft19": 0, "TLSv1.3draft20": 0, "TLSv1.3draft21": 0, "TLSv1.3draft22": 0, "TLSv1.3draft23": 5116, "TLSv1.3draft24": 0, "TLSv1.3draft25": 0, "TLSv1.3draft26": 0, "TLSv1.3draft27": 0, "TLSv1.3draft28": 0, "TLSv1.3": 7}, "versionmap_countAny_full_or_sh": {"SSLv3": 9, "TLSv1.0": 629707, "TLSv1.1": 390, "TLSv1.2": 1820656, "TLSv1.3draft18": 2594, "TLSv1.3draft19": 0, "TLSv1.3draft20": 0, "TLSv1.3draft21": 0, "TLSv1.3draft22": 0, "TLSv1.3draft23": 57246, "TLSv1.3draft24": 0, "TLSv1.3draft25": 0, "TLSv1.3draft26": 0, "TLSv1.3draft27": 0, "TLSv1.3draft28": 60, "TLSv1.3": 58314}, "full_latest": {"SSLv3": 0, "TLSv1.0": 4267, "TLSv1.1": 3, "TLSv1.2": 1640779, "TLSv1.3draft18": 2548, "TLSv1.3draft19": 0, "TLSv1.3draft20": 0, "TLSv1.3draft21": 0, "TLSv1.3draft22": 0, "TLSv1.3draft23": 13259, "TLSv1.3draft24": 0, "TLSv1.3draft25": 0, "TLSv1.3draft26": 0, "TLSv1.3draft27": 0, "TLSv1.3draft28": 60, "TLSv1.3": 57752}, "full_preferred_over_sh_latest": {"SSLv3": 8, "TLSv1.0": 626192, "TLSv1.1": 383, "TLSv1.2": 1800636, "TLSv1.3draft18": 2571, "TLSv1.3draft19": 0, "TLSv1.3draft20": 0, "TLSv1.3draft21": 0, "TLSv1.3draft22": 0, "TLSv1.3draft23": 16906, "TLSv1.3draft24": 0, "TLSv1.3draft25": 0, "TLSv1.3draft26": 0, "TLSv1.3draft27": 0, "TLSv1.3draft28": 60, "TLSv1.3": 58129}, "full_or_sh_latest": {"SSLv3": 8, "TLSv1.0": 627024, "TLSv1.1": 383, "TLSv1.2": 1800409, "TLSv1.3draft18": 2567, "TLSv1.3draft19": 0, "TLSv1.3draft20": 0, "TLSv1.3draft21": 0, "TLSv1.3draft22": 0, "TLSv1.3draft23": 16131, "TLSv1.3draft24": 0, "TLSv1.3draft25": 0, "TLSv1.3draft26": 0, "TLSv1.3draft27": 0, "TLSv1.3draft28": 60, "TLSv1.3": 58303}, "full_and_sh_latest": {"SSLv3": 0, "TLSv1.0": 93, "TLSv1.1": 0, "TLSv1.2": 35569, "TLSv1.3draft18": 2310, "TLSv1.3draft19": 0, "TLSv1.3draft20": 0, "TLSv1.3draft21": 0, "TLSv1.3draft22": 0, "TLSv1.3draft23": 4505, "TLSv1.3draft24": 0, "TLSv1.3draft25": 0, "TLSv1.3draft26": 0, "TLSv1.3draft27": 0, "TLSv1.3draft28": 0, "TLSv1.3": 7}, "multi_versions_full": 1718668, "multi_versions_full_or_sh": 2504877, "full": 1718668, "full_or_SH": 2504885, "full_and_SH": 63744, "443_refused": 359904, "all": 2960187}